fs/dimzipfs/__init__.py
fs/dimzipfs/dimzipfs.py
fs/dimzipfs/opener.py
fs/dimzipfs/py.typed
fs_dimzipfs-0.1.1.dist-info/entry_points.txt
fs_dimzipfs-0.1.1.dist-info/LICENSE
fs_dimzipfs-0.1.1.dist-info/METADATA
fs_dimzipfs-0.1.1.dist-info/WHEEL
fs_dimzipfs-0.1.1.dist-info/RECORD
